b10_transfer/__init__.py
b10_transfer/archive.py
b10_transfer/cache.py
b10_transfer/cleanup.py
b10_transfer/config.py
b10_transfer/constants.py
b10_transfer/core.py
b10_transfer/environment.py
b10_transfer/info.py
b10_transfer/logging_utils.py
b10_transfer/space_monitor.py
b10_transfer/utils.py
b10_transfer/vllm_cache.py
b10_transfer-0.3.17.dist-info/METADATA
b10_transfer-0.3.17.dist-info/WHEEL
b10_transfer-0.3.17.dist-info/entry_points.txt
b10_transfer-0.3.17.dist-info/RECORD
