Metadata-Version: 2.4
Name: b10-transfer
Version: 0.3.17
Summary: Distributed PyTorch file transfer for Baseten - Environment-aware, lock-free file transfer management
License: MIT
Keywords: pytorch,file-transfer,cache,machine-learning,inference
Author: Shounak Ray
Author-email: shounak.noreply@baseten.co
Maintainer: Fred Liu
Maintainer-email: fred.liu.noreply@baseten.co
Requires-Python: >=3.9,<4.0
Classifier: Development Status :: 4 - Beta
Classifier: Intended Audience :: Developers
Classifier: License :: OSI Approved :: MIT License
Classifier: Programming Language :: Python :: 3
Classifier: Programming Language :: Python :: 3.9
Classifier: Programming Language :: Python :: 3.10
Classifier: Programming Language :: Python :: 3.11
Classifier: Programming Language :: Python :: 3.12
Classifier: Programming Language :: Python :: 3.13
Classifier: Programming Language :: Python :: 3.14
Classifier: Topic :: Scientific/Engineering :: Artificial Intelligence
Classifier: Topic :: Software Development :: Libraries :: Python Modules
Requires-Dist: torch (>=2.0.0)
Project-URL: Documentation, https://docs.baseten.co/development/model/b10-transfer
Project-URL: Homepage, https://docs.baseten.co/development/model/b10-transfer
Project-URL: Repository, https://pypi.org/project/b10-transfer/
